odoo/addons/pos_escpos_status/README.rst
odoo/addons/pos_escpos_status/__init__.py
odoo/addons/pos_escpos_status/__manifest__.py
odoo/addons/pos_escpos_status/i18n/fr.po
odoo/addons/pos_escpos_status/i18n/it.po
odoo/addons/pos_escpos_status/i18n/pos_escpos_status.pot
odoo/addons/pos_escpos_status/readme/DESCRIPTION.rst
odoo/addons/pos_escpos_status/static/description/icon.png
odoo/addons/pos_escpos_status/static/description/index.html
odoo/addons/pos_escpos_status/static/src/js/ProxyStatus.js
odoo_addon_pos_escpos_status-16.0.1.0.1.dist-info/METADATA
odoo_addon_pos_escpos_status-16.0.1.0.1.dist-info/WHEEL
odoo_addon_pos_escpos_status-16.0.1.0.1.dist-info/top_level.txt
odoo_addon_pos_escpos_status-16.0.1.0.1.dist-info/RECORD
