Metadata-Version: 2.1
Name: odoo-addon-pos-escpos-status
Version: 16.0.1.0.1
Summary: Point of sale: fetch status for 'escpos' driver
Home-page: https://github.com/OCA/pos
Author: Odoo Community Association (OCA)
Author-email: support@odoo-community.org
License: AGPL-3
Platform: UNKNOWN
Classifier: Programming Language :: Python
Classifier: Framework :: Odoo
Classifier: Framework :: Odoo :: 16.0
Classifier: License :: OSI Approved :: GNU Affero General Public License v3
Requires-Python: >=3.10
Requires-Dist: odoo <16.1dev,>=16.0a
